{"cameraMode":{"drawMode":0,"name":"Shaded","section":"Shading Mode"},"sceneLighting":true,"audioPlay":false,"sceneViewState":{"m_AlwaysRefresh":false,"showFog":true,"showSkybox":true,"showFlares":true,"showImageEffects":true,"showParticleSystems":true,"showVisualEffectGraphs":true,"m_FxEnabled":true},"in2DMode":false,"pivot":{"x":-86.04801940917969,"y":21.968015670776368,"z":-0.31780850887298586},"rotation":{"x":-0.04419541731476784,"y":0.806989848613739,"z":-0.06089109554886818,"w":-0.5857738852500916},"size":59.509071350097659,"orthographic":false}